HMBasr/__init__.py
HMBasr/asr.py
HMBasr-0.0.18.dist-info/LICENSE
HMBasr-0.0.18.dist-info/METADATA
HMBasr-0.0.18.dist-info/WHEEL
HMBasr-0.0.18.dist-info/top_level.txt
HMBasr-0.0.18.dist-info/RECORD
