Metadata-Version: 2.1
Name: HMBasr
Version: 0.0.18
Summary: Automatic Speech Recognition
Home-page: UNKNOWN
Author: Lou Lély
Author-email: <loulely34@gmail.com>
License: UNKNOWN
Keywords: python,transcription,speech,speech to text,speech recognition,fr,asr
Platform: UNKNOWN
Classifier: Development Status :: 1 - Planning
Classifier: Intended Audience :: Developers
Classifier: Programming Language :: Python :: 3
Classifier: Operating System :: Unix
Classifier: Operating System :: MacOS :: MacOS X
Classifier: Operating System :: Microsoft :: Windows
License-File: LICENSE
Requires-Dist: torch
Requires-Dist: transformers
Requires-Dist: librosa
Requires-Dist: pyctcdecode
